{
  "actionMode" : "UNKNOWN",
  "actionType" : "BUILTIN",
  "codeName" : "Save",
  "dataAccessAction" : "NONE",
  "dynaModelFilePath" : "PSMODULES/task/PSDATAENTITIES/JobsInfo/PSDEACTIONS/Save.json",
  "logicName" : "Save",
  "name" : "Save",
  "getPSDEActionInput" : {
    "name" : "SaveInput",
    "getPSDEMethodDTO" : {
      "modelref" : true,
      "id" : "JobsInfoDTO"
    },
    "type" : "DTO"
  },
  "getPSDEActionReturn" : {
    "name" : "SaveResult",
    "type" : "VOID"
  },
  "builtinAction" : true
}