{
  "actionMode" : "GETDRAFT",
  "actionType" : "BUILTIN",
  "codeName" : "GetDraft",
  "dataAccessAction" : "CREATE",
  "dynaModelFilePath" : "PSMODULES/workflow/PSDATAENTITIES/WFUndoTask/PSDEACTIONS/GetDraft.json",
  "logicName" : "GetDraft",
  "name" : "GetDraft",
  "orderValue" : 41,
  "getPSDEActionInput" : {
    "name" : "GetDraftInput",
    "getPSDEMethodDTO" : {
      "modelref" : true,
      "id" : "WFUndoTaskDTO"
    },
    "type" : "DTO"
  },
  "getPSDEActionReturn" : {
    "name" : "GetDraftResult",
    "getPSDEMethodDTO" : {
      "modelref" : true,
      "id" : "WFUndoTaskDTO"
    },
    "type" : "DTO"
  },
  "builtinAction" : true
}